{
  "branch_name": "fn-646-keeper-cli-opentui-port",
  "bundles": [],
  "created_at": "2026-05-29T20:20:58.479393Z",
  "depends_on_epics": [],
  "id": "fn-646-keeper-cli-opentui-port",
  "last_validated_at": "2026-05-29T20:20:58.585040Z",
  "plan_review_status": "unknown",
  "plan_reviewed_at": null,
  "primary_repo": "/Users/mike/code/keeper",
  "queue_jump": false,
  "snippets": [],
  "status": "open",
  "title": "keeper cli opentui port",
  "touched_repos": [
    "/Users/mike/code/keeper"
  ],
  "updated_at": "2026-05-29T20:20:58.479393Z"
}
