{
  "approval": "pending",
  "branch_name": "fn-keeper-db-corruption-resilience",
  "bundles": [],
  "created_at": "2026-06-08T15:12:59.036213Z",
  "depends_on_epics": [],
  "id": "fn-746-keeper-db-corruption-resilience",
  "last_validated_at": "2026-06-08T15:12:59.156556Z",
  "primary_repo": "/Users/mike/code/keeper",
  "queue_jump": false,
  "snippets": [],
  "status": "open",
  "title": "Keeper db corruption resilience",
  "touched_repos": [
    "/Users/mike/code/keeper"
  ],
  "updated_at": "2026-06-08T15:12:59.036213Z"
}
